README.md
setup.py
parth/__init__.py
parth/parth.py
parth.egg-info/PKG-INFO
parth.egg-info/SOURCES.txt
parth.egg-info/dependency_links.txt
parth.egg-info/entry_points.txt
parth.egg-info/top_level.txt
parth/core/__init__.py
parth/core/colors.py
parth/core/importer.py
parth/core/param_map.py
parth/core/scanner.py
parth/core/utils.py
parth/plugins/__init__.py
parth/plugins/commoncrawl.py
parth/plugins/otx.py
parth/plugins/wayback.py