Metadata-Version: 2.1
Name: parth
Version: 0.2.0
Summary: Heuristics based vulnerable parameter scanner
Home-page: https://github.com/s0md3v/parth
Author: s0md3v
License: Apache-2.0 License
Download-URL: https://github.com/s0md3v/parth/archive/v0.2.0.zip
Keywords: hacking,vulnerability,security,scanning,pentesting
Platform: UNKNOWN
Classifier: Topic :: Security
Classifier: Operating System :: OS Independent
Classifier: License :: OSI Approved :: Apache Software License
Classifier: Programming Language :: Python :: 3
